math2eb/__init__.py
math2eb-0.1.1.dist-info/WHEEL
math2eb-0.1.1.dist-info/METADATA
math2eb-0.1.1.dist-info/RECORD
