Metadata-Version: 2.1
Name: math2eb
Version: 0.1.1
Summary: A better math module for python
Author: O.Plimer
Requires-Python: >=3.8,<4.0
Classifier: Programming Language :: Python :: 3
Classifier: Programming Language :: Python :: 3.10
Classifier: Programming Language :: Python :: 3.8
Classifier: Programming Language :: Python :: 3.9
